sccross/__init__.py
sccross/data.py
sccross/metrics.py
sccross/utils.py
sccross/models/__init__.py
sccross/models/data.py
sccross/models/layers.py
sccross/models/sccross.py
sccross/models/utils.py
sccross-1.0.7.1.dist-info/licenses/LICENSE
sccross-1.0.7.1.dist-info/WHEEL
sccross-1.0.7.1.dist-info/METADATA
sccross-1.0.7.1.dist-info/RECORD
