Metadata-Version: 2.2
Name: sccross
Version: 1.0.7.1
Summary: Single cell multi-omics cross modal generation, multi-omics simulation and perturbation
Keywords: bioinformatics,deep-learning,single-cell,single-cell-multiomics
Requires-Python: >=3.6
Classifier: Intended Audience :: Science/Research
Classifier: License :: OSI Approved :: MIT License
Classifier: Natural Language :: English
Classifier: Operating System :: MacOS :: MacOS X
Classifier: Operating System :: POSIX :: Linux
Classifier: Programming Language :: Python :: 3
Classifier: Programming Language :: Python :: 3.6
Classifier: Programming Language :: Python :: 3.7
Classifier: Programming Language :: Python :: 3.8
Classifier: Programming Language :: Python :: 3.9
Classifier: Topic :: Scientific/Engineering :: Bio-Informatics
License-File: LICENSE
Requires-Dist: numpy>=1.19
Requires-Dist: scipy==1.8.0
Requires-Dist: pandas>=1.1
Requires-Dist: matplotlib>=3.1.2
Requires-Dist: seaborn>=0.9
Requires-Dist: dill>=0.2.3
Requires-Dist: tqdm>=4.27
Requires-Dist: scikit-learn>=0.21.2
Requires-Dist: statsmodels>=0.10
Requires-Dist: parse>=1.3.2
Requires-Dist: networkx>=2
Requires-Dist: pynvml>=8.0.1
Requires-Dist: torch>=1.8
Requires-Dist: pytorch-ignite>=0.4.1
Requires-Dist: tensorboardX>=1.4
Requires-Dist: anndata>=0.7
Requires-Dist: scanpy>=1.5
Requires-Dist: pybedtools>=0.8.1
Requires-Dist: h5py>=2.10
Requires-Dist: sparse>=0.3.1
Requires-Dist: packaging>=16.8
Requires-Dist: leidenalg>=0.7
Requires-Dist: episcanpy>=0.3.2
Requires-Dist: sphinx<4 ; extra == "doc"
Requires-Dist: sphinx-autodoc-typehints<1.12 ; extra == "doc"
Requires-Dist: sphinx-copybutton ; extra == "doc"
Requires-Dist: nbsphinx ; extra == "doc"
Requires-Dist: sphinx-rtd-theme ; extra == "doc"
Requires-Dist: ipython ; extra == "doc"
Requires-Dist: jinja2<3.1 ; extra == "doc"
Requires-Dist: prompt-toolkit<3.0.0 ; extra == "doc"
Requires-Dist: plotly ; extra == "test"
Requires-Dist: pytest ; extra == "test"
Requires-Dist: pytest-cov ; extra == "test"
Project-URL: Github, https://github.com/Xiuhui-Yang/scCross
Provides-Extra: doc
Provides-Extra: test
